densratio/RuLSIF.py
densratio/__init__.py
densratio/core.py
densratio/density_ratio.py
densratio/helpers.py
densratio-0.3.0.dist-info/LICENSE
densratio-0.3.0.dist-info/METADATA
densratio-0.3.0.dist-info/WHEEL
densratio-0.3.0.dist-info/top_level.txt
densratio-0.3.0.dist-info/RECORD
