Metadata-Version: 2.1
Name: densratio
Version: 0.3.0
Summary: A Python Package for Density Ratio Estimation
Home-page: https://github.com/hoxo-m/densratio_py
Author: Koji Makiyama, Ameya Daigavane, Krzysztof Mierzejewski
Author-email: hoxo.smile@gmail.com
License: MIT + file LICENSE
Project-URL: Bug Reports, https://github.com/hoxo-m/densratio_py/issues
Project-URL: Source, https://github.com/hoxo-m/densratio_py
Keywords: density ratio estimation,anomaly detection,change point detection,covariate shift
Platform: UNKNOWN
Classifier: License :: OSI Approved :: MIT License
Classifier: Programming Language :: Python :: 3.9
Classifier: Programming Language :: Python :: 3.10
Classifier: Topic :: Scientific/Engineering :: Artificial Intelligence
License-File: LICENSE
Requires-Dist: numpy
